sapyens
