Metadata-Version: 1.1
Name: sapyens
Version: 0.2.1
Summary: SQLAlchemy & Pyramid enhancements
Home-page: https://github.com/fillest/sapyens
Author: Philipp Saveliev
Author-email: fsfeel@gmail.com
License: UNKNOWN
Platform: UNKNOWN
Classifier: Development Status :: 4 - Beta
Classifier: Framework :: Pyramid
Classifier: Intended Audience :: Developers
Classifier: License :: OSI Approved :: MIT License
Classifier: Programming Language :: Python
